py_libget/__init__.py
py_libget/package_manager.py
py_libget/parser.py
py_libget/version.py
py_libget/webhandler.py
py_libget-0.0.6.dist-info/LICENSE
py_libget-0.0.6.dist-info/METADATA
py_libget-0.0.6.dist-info/WHEEL
py_libget-0.0.6.dist-info/top_level.txt
py_libget-0.0.6.dist-info/RECORD
