Metadata-Version: 2.1
Name: py-libget
Version: 0.0.6
Summary: Module for handling libget packages.
Author-email: Lyfe <Lyfe@brewtools.dev>
License: LICENSE
Project-URL: homepage, https://github.com/fortheusers/py_libget
Project-URL: bug tracker, https://github.com/fortheusers/py_libget/issues
Project-URL: documentation, https://github.com/fortheusers/py_libget
Project-URL: repository, https://github.com/fortheusers/py_libget
Classifier: Development Status :: 1 - Planning
Classifier: Environment :: Console
Classifier: License :: OSI Approved :: GNU General Public License v3 or later (GPLv3+)
Classifier: Natural Language :: English
Classifier: Operating System :: OS Independent
Classifier: Programming Language :: Python :: 3.11
Requires-Python: >=3.11
License-File: LICENSE
